aurlcutter/__init__.py
aurlcutter/_base.py
aurlcutter/_exceptions.py
aurlcutter/_links.py
aurlcutter/_types.py
aurlcutter/_validators.py
aurlcutter/cutters/__init__.py
aurlcutter/cutters/chilpit.py
aurlcutter/cutters/dagd.py
aurlcutter/cutters/isgd.py
aurlcutter/cutters/osdb.py
aurlcutter/cutters/tinyurl.py
aurlcutter-0.0.1a1.dist-info/LICENSE.md
aurlcutter-0.0.1a1.dist-info/WHEEL
aurlcutter-0.0.1a1.dist-info/METADATA
aurlcutter-0.0.1a1.dist-info/RECORD
