Metadata-Version: 2.1
Name: aurlcutter
Version: 0.0.1a1
Summary: Asynchronous lib for making short urls
Home-page: https://github.com/mesiriak/aurlcutter
License: GPL-3.0
Author: Mesiriak
Author-email: iamzhv@gmail.com
Requires-Python: >=3.10,<4.0
Classifier: License :: OSI Approved :: GNU General Public License v3 (GPLv3)
Classifier: Programming Language :: Python :: 3
Classifier: Programming Language :: Python :: 3.10
Classifier: Programming Language :: Python :: 3.11
Requires-Dist: httpx (>=0.23.3,<0.24.0)
Project-URL: Repository, https://github.com/mesiriak/aurlcutter
